lbster-0.0.16.dist-info/licenses/LICENSE
lobster/__init__.py
lobster/_ensure_package.py
lobster/assets/__init__.py
lobster/assets/ab_vocab.txt
lobster/assets/pmlm_vocab.txt
lobster/assets/protein_vocab.txt
lobster/assets/3di_tokenizer/__init__.py
lobster/assets/3di_tokenizer/special_tokens_map.json
lobster/assets/3di_tokenizer/tokenizer_config.json
lobster/assets/3di_tokenizer/vocab.txt
lobster/assets/amino_acid_tokenizer/__init__.py
lobster/assets/amino_acid_tokenizer/special_tokens_map.json
lobster/assets/amino_acid_tokenizer/tokenizer.json
lobster/assets/amino_acid_tokenizer/tokenizer_config.json
lobster/assets/cdna_tokenizer/__init__.py
lobster/assets/cdna_tokenizer/special_tokens_map.json
lobster/assets/cdna_tokenizer/tokenizer_config.json
lobster/assets/cdna_tokenizer/vocab.txt
lobster/assets/codon_tables/codon_table.json
lobster/assets/codon_tables/vendor_codon_table.json
lobster/assets/concepts/biological_process_unique_values.txt
lobster/assets/concepts/cellular_component_unique_values.txt
lobster/assets/concepts/cluster_name_unique_values.txt
lobster/assets/concepts/members_unique_values.txt
lobster/assets/concepts/molecular_function_unique_values.txt
lobster/assets/concepts/organism_unique_values.txt
lobster/assets/concepts/rep_id_unique_values.txt
lobster/assets/concepts/taxon_id_unique_values.txt
lobster/assets/concepts/taxon_unique_values.txt
lobster/assets/concepts/unique_identifier_unique_values.txt
lobster/assets/cortex_ab_tokenizer/__init__.py
lobster/assets/cortex_ab_tokenizer/special_tokens_map.json
lobster/assets/cortex_ab_tokenizer/tokenizer_config.json
lobster/assets/cortex_ab_tokenizer/vocab.txt
lobster/assets/hyena_tokenizer/__init__.py
lobster/assets/hyena_tokenizer/special_tokens_map.json
lobster/assets/hyena_tokenizer/tokenizer_config.json
lobster/assets/hyena_tokenizer/vocab.txt
lobster/assets/latent_generator_tokenizer/special_tokens_map.json
lobster/assets/latent_generator_tokenizer/tokenizer.json
lobster/assets/latent_generator_tokenizer/tokenizer_config.json
lbster-0.0.16.dist-info/METADATA
lbster-0.0.16.dist-info/WHEEL
lbster-0.0.16.dist-info/entry_points.txt
lbster-0.0.16.dist-info/top_level.txt
lbster-0.0.16.dist-info/RECORD
