Metadata-Version: 2.4
Name: lbster
Version: 0.0.16
Summary: Language models for Biological Sequence Transformation and Evolutionary Representation.
Author-email: "Nathan C. Frey" <frey.nathan.nf1@gene.com>
Requires-Python: <3.13,>=3.11
License-File: LICENSE
Requires-Dist: pooch
Requires-Dist: torch
Requires-Dist: tqdm
Requires-Dist: lightning
Requires-Dist: torchmetrics
Requires-Dist: biopython
Requires-Dist: torchvision
Requires-Dist: universal_pathlib
Requires-Dist: pandas
Requires-Dist: scipy
Requires-Dist: pyarrow
Requires-Dist: s3fs[boto3]
Requires-Dist: biopandas
Requires-Dist: wandb
Requires-Dist: hydra-core
Requires-Dist: datasets>2
Requires-Dist: tokenizers
Requires-Dist: transformers>=4.24.0
Requires-Dist: scikit-learn
Requires-Dist: python-dotenv
Requires-Dist: torcheval
Requires-Dist: datasketch
Requires-Dist: peft
Requires-Dist: edlib
Requires-Dist: onnx
Requires-Dist: onnxscript
Requires-Dist: onnxruntime
Requires-Dist: einops
Requires-Dist: beignet[datasets]>=0.0.13
Requires-Dist: dotenv>=0.9.9
Requires-Dist: litdata>=0.2.49
Requires-Dist: seaborn>=0.13.2
Requires-Dist: dgeb>=0.2.0
Requires-Dist: huggingface-hub>=0.33.2
Requires-Dist: polars>=1.33.0
Requires-Dist: hydra-submitit-launcher>=1.2.0
Requires-Dist: rdkit>=2024.9.4
Provides-Extra: lg-cpu
Requires-Dist: biopandas==0.5.0.dev0; extra == "lg-cpu"
Requires-Dist: torch-geometric; extra == "lg-cpu"
Requires-Dist: torch-cluster; extra == "lg-cpu"
Requires-Dist: torch-scatter; extra == "lg-cpu"
Requires-Dist: torch_spline_conv; extra == "lg-cpu"
Requires-Dist: omegaconf; extra == "lg-cpu"
Requires-Dist: polars; extra == "lg-cpu"
Requires-Dist: optree; extra == "lg-cpu"
Requires-Dist: biotite; extra == "lg-cpu"
Requires-Dist: tensordict; extra == "lg-cpu"
Requires-Dist: loguru; extra == "lg-cpu"
Requires-Dist: icecream; extra == "lg-cpu"
Requires-Dist: mpmath; extra == "lg-cpu"
Requires-Dist: rotary-embedding-torch; extra == "lg-cpu"
Requires-Dist: matplotlib; extra == "lg-cpu"
Requires-Dist: boto3; extra == "lg-cpu"
Requires-Dist: botocore; extra == "lg-cpu"
Requires-Dist: lightning-utilities; extra == "lg-cpu"
Requires-Dist: mini3di; extra == "lg-cpu"
Requires-Dist: cpdb-protein; extra == "lg-cpu"
Provides-Extra: lg-gpu
Requires-Dist: biopandas==0.5.0.dev0; extra == "lg-gpu"
Requires-Dist: torch-geometric; extra == "lg-gpu"
Requires-Dist: torch-cluster; extra == "lg-gpu"
Requires-Dist: torch-scatter; extra == "lg-gpu"
Requires-Dist: torch_spline_conv; extra == "lg-gpu"
Requires-Dist: omegaconf; extra == "lg-gpu"
Requires-Dist: polars; extra == "lg-gpu"
Requires-Dist: optree; extra == "lg-gpu"
Requires-Dist: biotite; extra == "lg-gpu"
Requires-Dist: tensordict; extra == "lg-gpu"
Requires-Dist: loguru; extra == "lg-gpu"
Requires-Dist: icecream; extra == "lg-gpu"
Requires-Dist: mpmath; extra == "lg-gpu"
Requires-Dist: rotary-embedding-torch; extra == "lg-gpu"
Requires-Dist: matplotlib; extra == "lg-gpu"
Requires-Dist: boto3; extra == "lg-gpu"
Requires-Dist: botocore; extra == "lg-gpu"
Requires-Dist: lightning-utilities; extra == "lg-gpu"
Requires-Dist: mini3di; extra == "lg-gpu"
Requires-Dist: cpdb-protein; extra == "lg-gpu"
Provides-Extra: mgm
Requires-Dist: selfies>=2.1.2; extra == "mgm"
Provides-Extra: flash
Requires-Dist: flash-attn>=2.8.0.post2; sys_platform == "linux" and extra == "flash"
Requires-Dist: rotary-embedding-torch; extra == "flash"
Provides-Extra: mcp
Requires-Dist: mcp[cli]>=1.0.0; extra == "mcp"
Requires-Dist: fastmcp>=0.2.0; extra == "mcp"
Requires-Dist: python-Levenshtein>=0.20.0; extra == "mcp"
Requires-Dist: pydantic>=2.0.0; extra == "mcp"
Provides-Extra: trl
Requires-Dist: trl; extra == "trl"
Requires-Dist: accelerate; extra == "trl"
Dynamic: license-file
